Tele/Tele.py
Tele/__init__.py
telepy-0.0.31.dist-info/LICENSE
telepy-0.0.31.dist-info/METADATA
telepy-0.0.31.dist-info/WHEEL
telepy-0.0.31.dist-info/top_level.txt
telepy-0.0.31.dist-info/RECORD
