Metadata-Version: 2.1
Name: telepy
Version: 0.0.31
Summary: Telegram bot library
Home-page: https://gitlab.com/2411eliko/tele
Author: eliko
Author-email: eliko2411@hi2.in
License: UNKNOWN
Platform: UNKNOWN
Classifier: Programming Language :: Python :: 3
Classifier: License :: OSI Approved :: MIT License
Classifier: Operating System :: OS Independent
Requires-Python: ~=3.4
Requires-Dist: requests
